[
    {
        "type": "MOV",
        "x": 0,
        "y": 0,
        "z": 0,
        "g": "A"
    },
    {
        "type": "MOV",
        "x": 0,
        "y": 0,
        "z": 13,
        "g": "A"
    },
    {
        "type": "MOV",
        "x": 0,
        "y": 6,
        "z": 13,
        "g": "A"
    },
    {
        "type": "MOV",
        "x": 0,
        "y": 6,
        "z": 21,
        "g": "A"
    },
    {
        "type": "MOV",
        "x": 0,
        "y": 13,
        "z": 21,
        "g": "A"
    },
    {
        "type": "MOV",
        "x": 0,
        "y": 13,
        "z": 24,
        "g": "A"
    },
    {
        "type": "MOV",
        "x": 0,
        "y": 30,
        "z": 24,
        "g": "A"
    },
    {
        "type": "MOV",
        "x": 1,
        "y": 30,
        "z": 24,
        "g": "C"
    },
    {
        "type": "MOV",
        "x": 300,
        "y": 30,
        "z": 24,
        "g": "C"
    },
    {
        "type": "MOV",
        "x": 390,
        "y": 30,
        "z": 24,
        "g": "C"
    },
    {
        "type": "MOV",
        "x": 743,
        "y": 30,
        "z": 24,
        "g": "C"
    },
    {
        "type": "MOV",
        "x": 332,
        "y": 30,
        "z": 24,
        "g": "C"
    },
    {
        "type": "MOV",
        "x": 332,
        "y": 30,
        "z": 32,
        "g": "C"
    },
    {
        "type": "MOV",
        "x": 332,
        "y": 71,
        "z": 32,
        "g": "C"
    },
    {
        "type": "MOV",
        "x": 332,
        "y": 71,
        "z": 17,
        "g": "C"
    },
    {
        "type": "MOV",
        "x": 332,
        "y": 71,
        "z": 17,
        "g": "A"
    },
    {
        "type": "MOV",
        "x": 0,
        "y": 14,
        "z": 0,
        "g": "A"
    }
]